spr/__init__.py
spr-0.2.1.data/data/requirements-dev.txt
spr-0.2.1.data/data/requirements.txt
spr-0.2.1.dist-info/METADATA
spr-0.2.1.dist-info/RECORD
spr-0.2.1.dist-info/WHEEL
spr-0.2.1.dist-info/top_level.txt
