Metadata-Version: 2.1
Name: spr
Version: 0.2.1
Summary: A tiny Python package to parse spice raw data files
Home-page: https://github.com/goncalo-godwitlabs/spr
Author: goncalo-godwitlabs
Author-email: goncalo@godwitlabs.com
License: UNKNOWN
Project-URL: Source, https://github.com/goncalo-godwitlabs/spr
Project-URL: Bug Reports, https://github.com/goncalo-godwitlabs/spr/issues
Keywords: spice matplotlib rawspice raw
Platform: UNKNOWN
Classifier: Development Status :: 3 - Alpha
Classifier: Intended Audience :: Developers
Classifier: License :: OSI Approved :: MIT License
Classifier: Topic :: Scientific/Engineering :: Electronic Design Automation (EDA)
Classifier: Programming Language :: Python :: 2.7
Provides-Extra: dev
Requires-Dist: matplotlib (>=2.2.2)
Requires-Dist: numpy (>=1.14.2)
Provides-Extra: dev
Requires-Dist: matplotlib (>=2.2.2); extra == 'dev'
Requires-Dist: numpy (>=1.14.2); extra == 'dev'
Requires-Dist: pylint (>=1.8.4); extra == 'dev'
Requires-Dist: autopep8 (>=1.3.5); extra == 'dev'
Requires-Dist: ipython (>=5.6.0); extra == 'dev'
Requires-Dist: twine (>=1.11.0); extra == 'dev'
